kupala/__init__.py
kupala/applications.py
kupala/authentication.py
kupala/choices.py
kupala/dependencies.py
kupala/exceptions.py
kupala/files.py
kupala/passwords.py
kupala/py.typed
kupala/responses.py
kupala/routing.py
kupala/sessions.py
kupala/templating.py
kupala/asgi/__init__.py
kupala/asgi/request_limit.py
kupala/asgi/request_timeout.py
kupala/contrib/__init__.py
kupala/contrib/authentication/__init__.py
kupala/database/__init__.py
kupala/database/columns.py
kupala/database/dependencies.py
kupala/database/extension.py
kupala/database/manager.py
kupala/database/middleware.py
kupala/database/migrations.py
kupala/database/models.py
kupala/database/query.py
kupala/templates/.gitkeep
kupala-0.60.3.dist-info/METADATA
kupala-0.60.3.dist-info/WHEEL
kupala-0.60.3.dist-info/licenses/LICENSE
kupala-0.60.3.dist-info/RECORD
